torch_adapter-0.1.0.dist-info/METADATA
torch_adapter-0.1.0.dist-info/WHEEL
torch_adapter-0.1.0.dist-info/licenses/LICENSE
torch_adapter/__init__.py
torch_adapter/hub/__init__.py
torch_adapter/transforms/__init__.py
torch_adapter/transforms/composition.py
torch_adapter/transforms/transform_op.py
torch_adapter/transforms/util.py
torch_adapter/util.py
torch_adapter-0.1.0.dist-info/RECORD
