Metadata-Version: 2.1
Name: torch_adapter
Version: 0.1.0
Summary: This library offers an implementation of PyTorch’s preprocessing and inference steps using the OpenVINO API, effectively serving as an adapter for PyTorch.
Keywords: Python,PyTorch,openvino
Author-Email: LucaTamSapienza <tutordimatematica.ing@gmail.com>
License: Copyright (c) 2024 Luca Tam
Classifier: Development Status :: 4 - Beta
Classifier: Intended Audience :: Developers
Classifier: Programming Language :: Python :: 3.9
Project-URL: Repository, https://github.com/LucaTamSapienza/torch_adapter
Project-URL: Issues, https://github.com/LucaTamSapienza/torch_adapter/issues
Requires-Python: >=3.9
Requires-Dist: torch==2.3.0
Requires-Dist: numpy
Requires-Dist: torchvision==0.18.0
Requires-Dist: openvino
